DocTest/Ai/__init__.py
DocTest/Ai/prompts.py
DocTest/Ai/renderers.py
DocTest/Ai/responses.py
DocTest/DocumentRepresentation.py
DocTest/Downloader.py
DocTest/IgnoreAreaManager.py
DocTest/Ocr.py
DocTest/PdfStructureComparator.py
DocTest/PdfStructureModels.py
DocTest/PdfTest.py
DocTest/PrintJob.py
DocTest/PrintJobTests.py
DocTest/TextNormalization.py
DocTest/VisualTest.py
DocTest/__init__.py
DocTest/config.py
DocTest/llm/__init__.py
DocTest/llm/client.py
DocTest/llm/config.py
DocTest/llm/exceptions.py
DocTest/llm/prompts.py
DocTest/llm/types.py
robotframework_doctestlibrary-0.31.0.dist-info/METADATA
robotframework_doctestlibrary-0.31.0.dist-info/WHEEL
robotframework_doctestlibrary-0.31.0.dist-info/licenses/LICENSE
robotframework_doctestlibrary-0.31.0.dist-info/RECORD
