Metadata-Version: 2.4
Name: robotframework-doctestlibrary
Version: 0.31.0
Summary: A library for Visual Document Testing
License: Apache-2.0
License-File: LICENSE
Author: Many Kasiriha
Author-email: many.kasiriha@dbschenker.com
Maintainer: Many Kasiriha
Maintainer-email: many.kasiriha@dbschenker.com
Requires-Python: >=3.9.0,<4.0.0
Classifier: License :: OSI Approved :: Apache Software License
Classifier: Programming Language :: Python :: 3
Classifier: Programming Language :: Python :: 3.9
Classifier: Programming Language :: Python :: 3.10
Classifier: Programming Language :: Python :: 3.11
Classifier: Programming Language :: Python :: 3.12
Classifier: Programming Language :: Python :: 3.13
Classifier: Programming Language :: Python :: 3.14
Provides-Extra: ai
Requires-Dist: PyMuPDF (>=1.23.1,<1.25.0) ; python_version == "3.8"
Requires-Dist: PyMuPDF (>=1.26.0) ; python_version >= "3.9"
Requires-Dist: Wand
Requires-Dist: deepdiff (<8.0) ; python_version < "3.9"
Requires-Dist: deepdiff (>=6.0) ; python_version >= "3.12"
Requires-Dist: deepdiff ; python_version >= "3.9" and python_version < "3.12"
Requires-Dist: imutils
Requires-Dist: numpy (<1.25) ; python_version == "3.8"
Requires-Dist: numpy (>=1.25,<2.0) ; python_version == "3.9"
Requires-Dist: numpy (>=1.26) ; python_version >= "3.10" and python_version < "3.13"
Requires-Dist: numpy (>=2.1.0) ; python_version >= "3.13"
Requires-Dist: opencv-python-headless
Requires-Dist: parsimonious
Requires-Dist: pydantic-ai-slim[openai] ; extra == "ai"
Requires-Dist: pylibdmtx
Requires-Dist: pytesseract
Requires-Dist: python-dotenv ; extra == "ai"
Requires-Dist: pyzbar
Requires-Dist: robotframework (>=4)
Requires-Dist: robotframework-assertion-engine
Requires-Dist: scikit-image (<0.22) ; python_full_version <= "3.8.0"
Requires-Dist: scikit-image (>=0.22.0) ; python_version == "3.12"
Requires-Dist: scikit-image (>=0.25.0) ; python_version >= "3.13"
Requires-Dist: scikit-image ; python_full_version > "3.8.0" and python_version < "3.12"
Requires-Dist: scipy (<1.11) ; python_full_version <= "3.8.0"
Requires-Dist: scipy (>=1.11) ; python_version >= "3.12" and python_version < "4.0"
Requires-Dist: scipy ; python_full_version > "3.8.0" and python_version < "3.12"
Requires-Dist: setuptools ; python_version >= "3.12" and python_version < "4.0"
Project-URL: Homepage, https://github.com/manykarim/robotframework-doctestlibrary
